shpkg/__main__.py
shpkg/install.py
shpkg/list_pkg.py
shpkg/remove.py
shpkg/update.py
shpkg/update_all.py
shpkg-0.2.0.dist-info/LICENSE
shpkg-0.2.0.dist-info/METADATA
shpkg-0.2.0.dist-info/WHEEL
shpkg-0.2.0.dist-info/entry_points.txt
shpkg-0.2.0.dist-info/top_level.txt
shpkg-0.2.0.dist-info/RECORD
