Metadata-Version: 2.1
Name: shpkg
Version: 0.2.0
Summary: packaging made fun and easy
Author-email: sctech <gamerselimiko@gmail.com>
Project-URL: homepage, https://github.com/shpkg/shpkg
Classifier: Programming Language :: Python :: 3
Classifier: Programming Language :: Python :: 3.12
Classifier: License :: OSI Approved :: GNU Affero General Public License v3 or later (AGPLv3+)
Classifier: Operating System :: OS Independent
Requires-Python: >=3.12
License-File: LICENSE
Requires-Dist: requests
Requires-Dist: click
